{
  "tables": {
    "groups": {
      "G01": {
        "ID": "G01",
        "Name": "Teacher"
      },
      "G02": {
        "ID": "G02",
        "Name": "Staff"
      },
      "G03": {
        "ID": "G03",
        "Name": "Student"
      },
      "G04": {
        "ID": "G04",
        "Name": "Gryffindor"
      },
      "G05": {
        "ID": "G05",
        "Name": "Hufflepuff"
      },
      "G06": {
        "ID": "G06",
        "Name": "Ravenclaw"
      },
      "G07": {
        "ID": "G07",
        "Name": "Slytherin"
      },
      "G08": {
        "ID": "G08",
        "Name": "Mage"
      },
      "G09": {
        "ID": "G09",
        "Name": "Muggle"
      },
      "G10": {
        "ID": "G10",
        "Name": "Pet"
      }
    },
    "cardholders": {
      "C01": {
        "ID": "C01",
        "Name": "Albus Dumbledore",
        "Card": 1000112,
        "From": "2020-01-01",
        "To": "2020-12-31",
        "Groups": {
          "G01": true,
          "G02": false,
          "G03": false,
          "G04": true,
          "G05": true,
          "G06": true,
          "G07": false,
          "G08": false,
          "G09": false,
          "G10": false
        }
      },
      "C02": {
        "ID": "C02",
        "Name": "Tom Riddle",
        "Card": 2000101,
        "From": "2020-01-01",
        "To": "2020-12-31",
        "Groups": {
          "G01": false,
          "G03": false,
          "G04": false,
          "G05": true,
          "G06": false,
          "G07": false,
          "G08": false,
          "G09": false,
          "G10": true
        }
      },
      "C03": {
        "ID": "C03",
        "Name": "Harry Potter",
        "Card": 6000101,
        "From": "2020-01-01",
        "To": "2020-12-31",
        "Groups": {
          "G01": true,
          "G02": false,
          "G03": true,
          "G04": true,
          "G05": false,
          "G06": false,
          "G07": false,
          "G08": false,
          "G09": false,
          "G10": true
        }
      }
    }
  }
}